{
  "20250101": {
    "url": "https://www.bing.com/th?id=OHR.RioNewYear_EN-US7216341802_UHD.jpg",
    "copyright": "New Year's Eve fireworks over Copacabana Beach, Rio de Janeiro, Brazil (© Wagner Meier/Getty Images)",
    "copyrightlink": "https://www.bing.com/search?q=New+Year%27s+Eve&form=hpcapt&filters=HpDate%3a%2220241231_0800%22"
  },
  "20250102": {
    "url": "https://www.bing.com/th?id=OHR.PolarBearSwim_EN-US7610036047_UHD.jpg",
    "copyright": "Polar bears at play in the Arctic (© Ondrej Prosicky/Shutterstock)",
    "copyrightlink": "https://www.bing.com/search?q=New+Year%27s+Day&form=hpcapt&filters=HpDate%3a%2220250101_0800%22"
  }
}